universal_search/__init__.py
universal_search/cli.py
universal_search/core.py
universal_search_tool-1.2.1.dist-info/licenses/LICENSE
universal_search_tool-1.2.1.dist-info/METADATA
universal_search_tool-1.2.1.dist-info/WHEEL
universal_search_tool-1.2.1.dist-info/entry_points.txt
universal_search_tool-1.2.1.dist-info/top_level.txt
universal_search_tool-1.2.1.dist-info/RECORD
