Metadata-Version: 2.4
Name: universal-search-tool
Version: 1.2.1
Summary: 🔍 零配置通用搜索工具 - 支持多引擎的命令行搜索
Home-page: https://github.com/your-username/universal-search-tool
Author: Claude Code
Author-email: Universal Search Tool Contributors <your-email@example.com>
License: MIT License
Project-URL: Homepage, https://github.com/your-username/universal-search-tool
Project-URL: Documentation, https://github.com/your-username/universal-search-tool#readme
Project-URL: Repository, https://github.com/your-username/universal-search-tool.git
Project-URL: Bug Reports, https://github.com/your-username/universal-search-tool/issues
Keywords: search,cli,google,bing,duckduckgo,serpapi,terminal
Classifier: Development Status :: 5 - Production/Stable
Classifier: Intended Audience :: Developers
Classifier: Intended Audience :: End Users/Desktop
Classifier: Topic :: Internet :: WWW/HTTP :: Indexing/Search
Classifier: Topic :: Software Development :: Libraries :: Python Modules
Classifier: License :: OSI Approved :: MIT License
Classifier: Programming Language :: Python :: 3
Classifier: Programming Language :: Python :: 3.7
Classifier: Programming Language :: Python :: 3.8
Classifier: Programming Language :: Python :: 3.9
Classifier: Programming Language :: Python :: 3.10
Classifier: Programming Language :: Python :: 3.11
Classifier: Programming Language :: Python :: 3.12
Classifier: Operating System :: OS Independent
Classifier: Environment :: Console
Requires-Python: >=3.7
License-File: LICENSE
Requires-Dist: google-search-results>=2.4.2
Provides-Extra: dev
Requires-Dist: pytest>=6.0; extra == "dev"
Requires-Dist: black; extra == "dev"
Requires-Dist: flake8; extra == "dev"
Dynamic: author
Dynamic: home-page
Dynamic: license-file
Dynamic: requires-python
